test/__init__.py
test/test_jaeger_wf_propagator.py
test/test_wavefront_span.py
test/test_wavefront_tracer.py
wavefront_opentracing_sdk/__init__.py
wavefront_opentracing_sdk/span.py
wavefront_opentracing_sdk/span_context.py
wavefront_opentracing_sdk/tracer.py
wavefront_opentracing_sdk/propagation/__init__.py
wavefront_opentracing_sdk/propagation/http.py
wavefront_opentracing_sdk/propagation/jaeger_wavefront.py
wavefront_opentracing_sdk/propagation/propagator.py
wavefront_opentracing_sdk/propagation/registry.py
wavefront_opentracing_sdk/propagation/textmap.py
wavefront_opentracing_sdk/reporting/__init__.py
wavefront_opentracing_sdk/reporting/composite.py
wavefront_opentracing_sdk/reporting/console.py
wavefront_opentracing_sdk/reporting/reporter.py
wavefront_opentracing_sdk/reporting/wavefront.py
wavefront_opentracing_sdk/sampling/__init__.py
wavefront_opentracing_sdk/sampling/composite.py
wavefront_opentracing_sdk/sampling/constant.py
wavefront_opentracing_sdk/sampling/duration.py
wavefront_opentracing_sdk/sampling/rate.py
wavefront_opentracing_sdk/sampling/sampler.py
wavefront_opentracing_sdk_python-2.3.4.dist-info/LICENSE
wavefront_opentracing_sdk_python-2.3.4.dist-info/METADATA
wavefront_opentracing_sdk_python-2.3.4.dist-info/WHEEL
wavefront_opentracing_sdk_python-2.3.4.dist-info/top_level.txt
wavefront_opentracing_sdk_python-2.3.4.dist-info/RECORD
