Metadata-Version: 2.1
Name: wavefront-opentracing-sdk-python
Version: 2.3.4
Summary: Tanzu Observability Opentracing SDK for Python.
Home-page: https://github.com/wavefrontHQ/wavefront-opentracing-sdk-python
Author: Tanzu Observability by Wavefront
Author-email: chitimba@wavefront.com
License: Apache-2.0
Keywords: OpenTracing,OpenTracing SDK,Wavefront,Wavefront SDK,Tanzu Observability,Tanzu Observability SDK
Platform: UNKNOWN
Classifier: License :: OSI Approved :: Apache Software License
Classifier: Programming Language :: Python :: 3.7
Classifier: Programming Language :: Python :: 3.8
Classifier: Programming Language :: Python :: 3.9
Classifier: Programming Language :: Python :: 3.10
License-File: LICENSE
Requires-Dist: opentracing (>=2.0)
Requires-Dist: wavefront-pyformance (>=1.3)
Requires-Dist: wavefront-sdk-python (>=1.8.0)
